<?xml version="1.0" encoding="utf-8" ?>
<Defs>

<!-- Red -->

 <HediffDef>
    <defName>HedRedBeanMan</defName>
    <label>Racial Trait: Standard Bean</label>
	<description>Red bean men are the most standard bean man color. They tend to be friendly and they have an affinity towards plants, but are not generally good workers otherwise.</description>		
    <initialSeverity>1</initialSeverity>
  	<defaultLabelColor>(0.47,0.87,0.47)</defaultLabelColor>      	
	<hediffClass>HediffWithComps</hediffClass>
    <isBad>false</isBad>
    <stages>
      <li>
		<statOffsets>
			  <PlantWorkSpeed>0.15</PlantWorkSpeed>
			  <SocialImpact>0.10</SocialImpact>
			  <WorkSpeedGlobal>-0.10</WorkSpeedGlobal>
		</statOffsets>		
      </li>
    </stages>
  </HediffDef>    
  
  <ThoughtDef>
    <defName>ThoughtRedBeanMan</defName>
    <workerClass>ThoughtWorker_Hediff</workerClass>
    <hediff>HedRedBeanMan</hediff>
    <stages>
      <li>
        <label>Red Bean Man</label>
        <description>What could be better than being a bean man?</description>
        <baseMoodEffect>5</baseMoodEffect>
      </li>
    </stages>
  </ThoughtDef>

<!-- Bulborb -->

 <HediffDef>
    <defName>HedBulborbBeanMan</defName>
    <label>Racial Trait: Bulborb Bean</label>
	<description>Bulborb Bean Men are much better with animals than other bean men, but are not very good with plant work.</description>		
    <initialSeverity>1</initialSeverity>
  	<defaultLabelColor>(0.47,0.87,0.47)</defaultLabelColor>      	
	<hediffClass>HediffWithComps</hediffClass>
    <isBad>false</isBad>
    <stages>
      <li>
		<statOffsets>
			  <PlantWorkSpeed>-0.25</PlantWorkSpeed>
			  <PlantHarvestYield>-0.15</PlantHarvestYield>
		</statOffsets>		
		<statFactors>
			  <TameAnimalChance>1.2</TameAnimalChance>
			  <TrainAnimalChance>1.2</TrainAnimalChance>
			  <BondAnimalChanceFactor>2</BondAnimalChanceFactor>
		</statFactors>		
      </li>
    </stages>
  </HediffDef>
  
<!-- Shiny -->
  
 <HediffDef>
    <defName>HedShinyBeanMan</defName>
    <label>Racial Trait: Shiny Bean</label>
	<description>A truly rare shiny bean man. Hold him close.</description>		
    <initialSeverity>1</initialSeverity>
  	<defaultLabelColor>(255,215,0)</defaultLabelColor>      	
	<hediffClass>HediffWithComps</hediffClass>
    <isBad>false</isBad>
    <stages>
      <li>
		<statOffsets>
			  <WorkSpeedGlobal>2</WorkSpeedGlobal>
			  <MoveSpeed>1.5</MoveSpeed>
			  <SocialImpact>2</SocialImpact>
		      <MeleeDodgeChance>25</MeleeDodgeChance>
			  <PawnBeauty>2</PawnBeauty>
		</statOffsets>		
      </li>
    </stages>
  </HediffDef>
  
  <ThoughtDef>
    <defName>ThoughtShinyBeanMan</defName>
    <workerClass>ThoughtWorker_Hediff</workerClass>
    <hediff>HedShinyBeanMan</hediff>
    <stages>
      <li>
        <label>Shiny Bean Man</label>
        <description>I am a king amongst bean men. Truly the pinnacle of creation.</description>
        <baseMoodEffect>20</baseMoodEffect>
      </li>
    </stages>
  </ThoughtDef>
  
<!-- Blue -->

 <HediffDef>
    <defName>HedBlueBeanMan</defName>
    <label>Racial Trait: Chill Bean</label>
	<description>Blue Bean Men are chill and friendly, but also lazy.</description>		
    <initialSeverity>1</initialSeverity>
  	<defaultLabelColor>(0.47,0.87,0.47)</defaultLabelColor>      	
	<hediffClass>HediffWithComps</hediffClass>
    <isBad>false</isBad>
    <stages>
      <li>
		<statOffsets>
			  <MentalBreakThreshold>-0.15</MentalBreakThreshold>
			  <SocialImpact>0.35</SocialImpact>
			  <WorkSpeedGlobal>-0.25</WorkSpeedGlobal>
		</statOffsets>		
      </li>
    </stages>
  </HediffDef>

<!-- Orange -->
 <HediffDef>
    <defName>HedOrangeBeanMan</defName>
    <label>Racial Trait: Mean Bean</label>
	<description>Orange bean men savor the thrill of melee combat.</description>		
    <initialSeverity>1</initialSeverity>
  	<defaultLabelColor>(0.47,0.87,0.47)</defaultLabelColor>      	
	<hediffClass>HediffWithComps</hediffClass>
    <isBad>false</isBad>
    <stages>
      <li>		
			<painFactor>0.9</painFactor>
		<statOffsets>
			<SocialImpact>-0.15</SocialImpact>
			<MeleeHitChance>4</MeleeHitChance>
		    <MeleeDodgeChance>12</MeleeDodgeChance>
			</statOffsets>			
      </li>
    </stages>
  </HediffDef>

<!-- Green -->
 <HediffDef>
    <defName>HedGreenBeanMan</defName>
    <label>Racial Trait: Green Bean</label>
	<description>Green bean men have a great affinity for life, but refuse to commit any acts of violence.</description>		
    <initialSeverity>1</initialSeverity>
  	<defaultLabelColor>(0.47,0.87,0.47)</defaultLabelColor>      	
	<hediffClass>HediffWithComps</hediffClass>
    <isBad>false</isBad>
    <stages>
      <li>
		<statOffsets>	
			  <PlantHarvestYield>0.3</PlantHarvestYield>
			  <PlantWorkSpeed>0.35</PlantWorkSpeed>	
		</statOffsets>				  
      </li>
    </stages>
  </HediffDef>
  
<!-- Coffee -->
 <HediffDef>
    <defName>HedCoffeeBeanMan</defName>
    <label>Racial Trait: Manic Bean</label>
	<description>Coffee bean men operate in a constant manic state- moving and working quickly, but also nearly always on the edge of a breakdown.</description>		
    <initialSeverity>1</initialSeverity>
  	<defaultLabelColor>(0.47,0.87,0.47)</defaultLabelColor>      	
	<hediffClass>HediffWithComps</hediffClass>
    <isBad>false</isBad>
    <stages>
      <li>
		<statOffsets>	
			  <MentalBreakThreshold>0.2</MentalBreakThreshold>
			  <WorkSpeedGlobal>0.3</WorkSpeedGlobal>	
		</statOffsets>	
            <capMods>
              <li>
                <capacity>Moving</capacity>
                <offset>0.15</offset>
              </li>
            </capMods>
      </li>
    </stages>
  </HediffDef>
  
<!-- Purple -->  
 <HediffDef>
    <defName>HedPurpleBeanMan</defName>
    <label>Racial Trait: Magic Bean</label>
	<description>Purple bean men are significantly more attuned to the flow of magic and psychic energy around them, for better and for worse.</description>		
    <initialSeverity>1</initialSeverity>
  	<defaultLabelColor>(0.47,0.87,0.47)</defaultLabelColor>      	
	<hediffClass>HediffWithComps</hediffClass>
    <isBad>false</isBad>
    <stages>
      <li>
		<statOffsets>	
          <PsychicSensitivity>0.5</PsychicSensitivity>
		</statOffsets>	
      </li>
    </stages>
	<modExtensions>
		<li Class="TorannMagic.TMDefs.DefModExtension_HediffEnchantments">
			<stages>
				<li>
					<minSeverity>0</minSeverity>
					<maxSeverity>100</maxSeverity>
					<enchantments>
						<mpRegenRate>0.5</mpRegenRate>
						<arcaneDmg>0.1</arcaneDmg>
						<maxMP>0.25</maxMP>
					</enchantments>
				</li>
			</stages>
		</li>
	</modExtensions>
  </HediffDef>  
  
 <!-- Black -->
 <HediffDef>
    <defName>HedBlackBeanMan</defName>
    <label>Racial Trait: Grumpy Bean</label>
	<description>Coffee bean men operate in a constant manic state- moving and working quickly, but also nearly always on the edge of a breakdown.</description>		
    <initialSeverity>1</initialSeverity>
  	<defaultLabelColor>(0.47,0.87,0.47)</defaultLabelColor>      	
	<hediffClass>HediffWithComps</hediffClass>
    <isBad>false</isBad>
    <stages>
      <li>
		<statOffsets>	
			  <ResearchSpeed>0.5</ResearchSpeed> 	
			<SocialImpact>-0.25</SocialImpact>
		</statOffsets>	
      </li>
    </stages>
  </HediffDef> 
  
  <ThoughtDef>
    <defName>ThoughtBlackBeanMan</defName>
    <workerClass>ThoughtWorker_Hediff</workerClass>
    <hediff>HedBlackBeanMan</hediff>
    <stages>
      <li>
        <label>Black Bean Man</label>
        <description>I am surrounded by idiots.</description>
        <baseMoodEffect>-5</baseMoodEffect>
      </li>
    </stages>
  </ThoughtDef>
  
 <!-- Silver -->
 <HediffDef>
    <defName>HedSilverBeanMan</defName>
    <label>Racial Trait: Healing Bean</label>
	<description>Silver bean men work as healers among the bean men. Their skills in combat, however, leave much to be desired.</description>		
    <initialSeverity>1</initialSeverity>
  	<defaultLabelColor>(0.47,0.87,0.47)</defaultLabelColor>      	
	<hediffClass>HediffWithComps</hediffClass>
    <isBad>false</isBad>
    <stages>
      <li>
		<statOffsets>
			<AimingDelayFactor>0.50</AimingDelayFactor>
			<MeleeHitChance>-15</MeleeHitChance>
			<ShootingAccuracyPawn>-15.0</ShootingAccuracyPawn>
			<MedicalTendQuality>0.33</MedicalTendQuality>
			<MedicalTendSpeed>0.67</MedicalTendSpeed>
			<MedicalOperationSpeed>0.67</MedicalOperationSpeed>
		</statOffsets>	
      </li>
    </stages>
  </HediffDef> 
 
<!-- Whiptongue -->

 <HediffDef>
    <defName>HedWhiptongueBeanMan</defName>
    <label>Racial Trait: Licky Bean</label>
	<description>Whiptongue Bean Men have unusually long tongues which they can use in combat.</description>		
    <initialSeverity>1</initialSeverity>
  	<defaultLabelColor>(0.47,0.87,0.47)</defaultLabelColor>      	
	<hediffClass>HediffWithComps</hediffClass>
    <isBad>false</isBad>
		<comps>
		  <li Class="MVCF.Comps.HediffCompProperties_ExtendedVerbGiver">
						<verbs>
							<li>
								<verbClass>Verb_Shoot</verbClass>
								<accuracyTouch>0.95</accuracyTouch>
								<accuracyShort>0.75</accuracyShort>
								<accuracyMedium>0.65</accuracyMedium>
								<accuracyLong>0.55</accuracyLong>
								<hasStandardCommand>true</hasStandardCommand>
								<defaultProjectile>Lick</defaultProjectile>
								<warmupTime>1.1</warmupTime>
								<range>9</range>				
								<soundCast>Lick</soundCast>
								<muzzleFlashScale>0</muzzleFlashScale>
								<label>whiptongue lick</label>
								<commonality>1</commonality>
							</li>
						</verbs>
						<verbProps>
							<li>
								<label>whiptongue lick</label>
								<draw>false</draw>
								<canBeToggled>true</canBeToggled>
							</li>
						</verbProps>
					</li>
		</comps>
    <stages>
      <li>
		<statOffsets>
          <AimingDelayFactor>-0.2</AimingDelayFactor>
          <ShootingAccuracyPawn>4</ShootingAccuracyPawn>
		  <MeleeHitChance>-8</MeleeHitChance>
		</statOffsets>		
      </li>
    </stages>
  </HediffDef>     
  
 <!-- Stinky -->
 <HediffDef>
    <defName>HedStinkyBeanMan</defName>
    <label>Racial Trait: Stinky Bean</label>
	<description>Nobody likes a stinky bean.</description>		
    <initialSeverity>1</initialSeverity>
  	<defaultLabelColor>(0.47,0.87,0.47)</defaultLabelColor>      	
	<hediffClass>HediffWithComps</hediffClass>
    <isBad>false</isBad>
    <comps>
	  <li Class="VFECore.HediffCompProperties_Spreadable">
		<radiusToSpread>0</radiusToSpread>
		<severityToInfect>0</severityToInfect>
		<baseDiseaseContractChance>0</baseDiseaseContractChance>
		<spreadingTickInterval>300000~600000</spreadingTickInterval>
		<socialInteractionTransmissionChance>0</socialInteractionTransmissionChance>
		<requiresLineOfSightToSpread>true</requiresLineOfSightToSpread>
		<speciesCanCatch>
			<li>Humanlike</li>
		</speciesCanCatch>
		<fleckDefOnPawn>StinkyMote</fleckDefOnPawn>
		<fleckSpawnInterval>25~50</fleckSpawnInterval>
		<fleckColor>(255,255,255)</fleckColor>
		<fleckScale>1.0</fleckScale>
		<spreadingMessageWarningKey>VFEM.BlackPlagueSpreadedFurther</spreadingMessageWarningKey>
	  </li>
		<li Class="AnimalBehaviours.HediffCompProperties_ThoughtEffecter">
			<radius>8</radius>
			<tickInterval>1000</tickInterval>
			<thoughtDef>StinkyBeanThought</thoughtDef>
		</li>
    </comps>
    <stages>
      <li>
		<statOffsets>
			<SocialImpact>-0.4</SocialImpact>
			<PawnBeauty>-2</PawnBeauty>
			<ToxicSensitivity>-0.6</ToxicSensitivity>
		</statOffsets>	
      </li>
    </stages>
  </HediffDef>   
  
  <ThoughtDef>
    <defName>StinkyBeanThought</defName>
    <durationDays>0.5</durationDays>
    <stages>
      <li>
        <label>horrible smell</label>
        <description>Why did we let that horrible smelling bean man in here?</description>
        <baseMoodEffect>-5</baseMoodEffect>
      </li>
    </stages>
  </ThoughtDef>  
  
<!-- Bertie Bott's -->

 <HediffDef>
    <defName>HedBottBeanMan</defName>
    <label>Racial Trait: Every Flavor Bean</label>
	<description>This bean man randomly deals with the effects of Bertie Bott's Every Flavor Beans.</description>		
    <initialSeverity>1</initialSeverity>
  	<defaultLabelColor>(0.47,0.87,0.47)</defaultLabelColor>      	
	<hediffClass>HediffWithComps</hediffClass>
    <isBad>false</isBad>
    <stages>
      <li>
        <hediffGivers>
          <li Class="HediffGiver_Random">
            <hediff>Hediff_BertieBottBeanManBuildup</hediff>
            <mtbDays>15</mtbDays>
          </li>
        </hediffGivers>
      </li>
    </stages>
  </HediffDef>    

 <!-- Cave -->
 <HediffDef>
    <defName>HedCaveBeanMan</defName>
    <label>Racial Trait: Blind Bean</label>
	<description>Cave Bean Men are adapted to living underground. However, their eyes are completely vestigial and they lack the ability to see. Not even bionics can cure this.</description>		
    <initialSeverity>1</initialSeverity>
  	<defaultLabelColor>(0.47,0.87,0.47)</defaultLabelColor>      	
	<hediffClass>HediffWithComps</hediffClass>
    <isBad>false</isBad>
    <stages>
      <li>
		<capMods>
		  <li>
			<capacity>Sight</capacity>
			<setMax>0</setMax>
		  </li>
		</capMods>
		<statOffsets>
			<MiningSpeed>0.30</MiningSpeed>
			<MiningYield>0.15</MiningYield>
		</statOffsets>	
      </li>
    </stages>
  </HediffDef>   
 
 <!-- Chili -->
 <HediffDef>
    <defName>HedChiliBeanMan</defName>
    <label>Racial Trait: Spicy Bean</label>
	<description>Spicy Bean Men are well adapted for living in warm environments. They are also known for their fiery personalities.</description>		
    <initialSeverity>1</initialSeverity>
  	<defaultLabelColor>(0.47,0.87,0.47)</defaultLabelColor>      	
	<hediffClass>HediffWithComps</hediffClass>
    <isBad>false</isBad>
    <stages>
      <li>
        <socialFightChanceFactor>2.5</socialFightChanceFactor>
		<statOffsets>
			<ComfyTemperatureMin>15</ComfyTemperatureMin>
			<ComfyTemperatureMax>20</ComfyTemperatureMax>
		</statOffsets>	
      </li>
    </stages>
  </HediffDef>  








 
</Defs>